dracalusb/__init__.py
dracalusb/builder.py
dracalusb-0.1.3.dist-info/LICENSE
dracalusb-0.1.3.dist-info/METADATA
dracalusb-0.1.3.dist-info/WHEEL
dracalusb-0.1.3.dist-info/RECORD
