Metadata-Version: 2.1
Name: dracalusb
Version: 0.1.3
Summary: Python wrapper for `dracal-usb-get` command line utility from Dracal Technologies.
Home-page: https://github.com/mrasore98/dracalusb
Author: Mathias Alexander
Author-email: mathias.alexander@irhythmtech.com
Requires-Python: >=3.12,<4.0
Classifier: Programming Language :: Python :: 3
Classifier: Programming Language :: Python :: 3.12
Project-URL: Repository, https://github.com/mrasore98/dracalusb
